bilbyai/__init__.py
bilbyai/quant/__init__.py
bilbyai/quant/constants/__init__.py
bilbyai/quant/constants/keywords.json
bilbyai/quant/constants/keywords.py
bilbyai/quant/date_wrangler.py
bilbyai/quant/ml/__init__.py
bilbyai/quant/ml/models/__init__.py
bilbyai/quant/ml/models/demand_supply_model_v3.joblib
bilbyai/quant/ml/models/impact_model_v3.joblib
bilbyai/quant/ml/models/load_models.py
bilbyai/quant/pipes/__init__.py
bilbyai/quant/pipes/basic.py
bilbyai/quant/processes/__init__.py
bilbyai/quant/processes/elastic.py
bilbyai/quant/schemas/__init__.py
bilbyai/quant/schemas/base_briefing_document.py
bilbyai/quant/schemas/commodity_briefing_document.py
bilbyai/quant/schemas/equity_briefing_document.py
bilbyai/quant/utils.py
bilbyai_quant-0.1.0.dist-info/METADATA
bilbyai_quant-0.1.0.dist-info/WHEEL
bilbyai_quant-0.1.0.dist-info/RECORD
