Metadata-Version: 2.1
Name: bilbyai-quant
Version: 0.1.0
Summary: A Python package for quant research.
Author: David Lee
Author-email: leetdavidu@gmail.com
Requires-Python: >=3.9
Classifier: Programming Language :: Python :: 3
Classifier: Programming Language :: Python :: 3.9
Classifier: Programming Language :: Python :: 3.10
Classifier: Programming Language :: Python :: 3.11
Classifier: Programming Language :: Python :: 3.12
Requires-Dist: elasticsearch (==8.13.1)
Requires-Dist: joblib (==1.4.2)
Requires-Dist: numpy (==1.26.4)
Requires-Dist: pandas (==2.2.2)
Requires-Dist: pyarrow (==16.0.0)
Requires-Dist: pydantic (==2.7.1)
Requires-Dist: torch (==2.3.0)
